kand-0.2.2.dist-info/METADATA
kand-0.2.2.dist-info/WHEEL
kand-0.2.2.dist-info/licenses/LICENSE-APACHE
kand-0.2.2.dist-info/licenses/LICENSE-MIT
kand/py.typed
kand/__init__.py
kand/_kand.pyi
kand/_kand.cpython-39-aarch64-linux-gnu.so
kand-0.2.2.dist-info/RECORD
