Metadata-Version: 2.4
Name: kand
Version: 0.2.2
Classifier: License :: OSI Approved :: MIT License
Classifier: License :: OSI Approved :: Apache Software License
Classifier: Programming Language :: Rust
Classifier: Programming Language :: Python :: Implementation :: CPython
Classifier: Programming Language :: Python :: Implementation :: PyPy
Classifier: Programming Language :: Python
Classifier: Programming Language :: Python :: 3.8
Classifier: Programming Language :: Python :: 3.9
Classifier: Programming Language :: Python :: 3.10
Classifier: Programming Language :: Python :: 3.11
Classifier: Programming Language :: Python :: 3.12
Classifier: Programming Language :: Python :: 3.13
Classifier: Programming Language :: Python :: 3 :: Only
Requires-Dist: numpy>=1.24.0,<1.26.0 ; python_full_version < '3.9'
Requires-Dist: numpy>=1.26.0 ; python_full_version >= '3.9'
License-File: LICENSE-APACHE
License-File: LICENSE-MIT
Summary: A high-performance technical analysis library written in Rust with Python bindings.
Keywords: ta,ta-lib,finance,quant,indicator,technical-analysis
Author: CtrlX <gitctrlx@gmail.com>
Author-email: CtrlX <gitctrlx@gmail.com>
License: Apache-2.0 OR MIT
Requires-Python: >=3.8
Project-URL: Repository, https://github.com/rust-ta/kand
Project-URL: Documentation, https://docs.rs/kand
Project-URL: Changelog, https://github.com/rust-ta/kand/blob/main/CHANGELOG.md
Project-URL: Releases, https://github.com/rust-ta/kand/releases
